iodata/__init__.py
iodata/__main__.py
iodata/_version.py
iodata/api.py
iodata/attrutils.py
iodata/basis.py
iodata/convert.py
iodata/docstrings.py
iodata/iodata.py
iodata/orbitals.py
iodata/overlap.py
iodata/overlap_cartpure.py
iodata/periodic.py
iodata/prepare.py
iodata/utils.py
iodata/formats/__init__.py
iodata/formats/charmm.py
iodata/formats/chgcar.py
iodata/formats/cp2klog.py
iodata/formats/cube.py
iodata/formats/extxyz.py
iodata/formats/fchk.py
iodata/formats/fcidump.py
iodata/formats/gamess.py
iodata/formats/gaussianinput.py
iodata/formats/gaussianlog.py
iodata/formats/gromacs.py
iodata/formats/json_qcschema.py
iodata/formats/locpot.py
iodata/formats/mol2.py
iodata/formats/molden.py
iodata/formats/molekel.py
iodata/formats/mwfn.py
iodata/formats/orcalog.py
iodata/formats/pdb.py
iodata/formats/poscar.py
iodata/formats/qchemlog.py
iodata/formats/sdf.py
iodata/formats/wfn.py
iodata/formats/wfx.py
iodata/formats/xyz.py
iodata/inputs/__init__.py
iodata/inputs/common.py
iodata/inputs/gaussian.py
iodata/inputs/orca.py
iodata/test/__init__.py
iodata/test/common.py
iodata/test/test_api.py
iodata/test/test_attrutils.py
iodata/test/test_basis.py
iodata/test/test_charmm.py
iodata/test/test_chgcar.py
iodata/test/test_cli.py
iodata/test/test_convert.py
iodata/test/test_cp2klog.py
iodata/test/test_cube.py
iodata/test/test_extxyz.py
iodata/test/test_fchk.py
iodata/test/test_fcidump.py
iodata/test/test_gamess.py
iodata/test/test_gaussianinput.py
iodata/test/test_gaussianlog.py
iodata/test/test_gromacs.py
iodata/test/test_inputs.py
iodata/test/test_iodata.py
iodata/test/test_json_qcschema.py
iodata/test/test_locpot.py
iodata/test/test_mol2.py
iodata/test/test_molden.py
iodata/test/test_molekel.py
iodata/test/test_mwfn.py
iodata/test/test_orbitals.py
iodata/test/test_orcalog.py
iodata/test/test_overlap.py
iodata/test/test_pdb.py
iodata/test/test_poscar.py
iodata/test/test_prepare.py
iodata/test/test_qchemlog.py
iodata/test/test_sdf.py
iodata/test/test_utils.py
qc_iodata-1.0.0a8.dist-info/licenses/LICENSE.txt
qc_iodata-1.0.0a8.dist-info/METADATA
qc_iodata-1.0.0a8.dist-info/WHEEL
qc_iodata-1.0.0a8.dist-info/entry_points.txt
qc_iodata-1.0.0a8.dist-info/top_level.txt
qc_iodata-1.0.0a8.dist-info/RECORD
