Metadata-Version: 2.4
Name: qc-iodata
Version: 1.0.0a8
Summary: Python Input and Output Library for Quantum Chemistry
Author-email: HORTON-ChemTools Dev Team <horton.chemtools@gmail.com>
License:                    GNU LESSER GENERAL PUBLIC LICENSE
Project-URL: Documentation, https://iodata.readthedocs.io/en/latest/
Project-URL: Issues, https://github.com/theochem/iodata/issues/
Project-URL: Source, https://github.com/theochem/iodata/
Classifier: Development Status :: 3 - Alpha
Classifier: Environment :: Console
Classifier: Intended Audience :: Education
Classifier: Intended Audience :: Science/Research
Classifier: License :: OSI Approved :: GNU General Public License v3 or later (GPLv3+)
Classifier: Operating System :: POSIX :: Linux
Classifier: Operating System :: MacOS
Classifier: Operating System :: Microsoft :: Windows
Classifier: Programming Language :: Python :: 3
Classifier: Programming Language :: Python :: 3 :: Only
Classifier: Programming Language :: Python :: 3.9
Classifier: Programming Language :: Python :: 3.10
Classifier: Programming Language :: Python :: 3.11
Classifier: Programming Language :: Python :: 3.12
Classifier: Programming Language :: Python :: 3.13
Classifier: Topic :: File Formats
Classifier: Topic :: Scientific/Engineering :: Physics
Classifier: Topic :: Scientific/Engineering :: Chemistry
Requires-Python: >=3.9
License-File: LICENSE.txt
Requires-Dist: numpy>=1.26.4
Requires-Dist: scipy>=1.13.1
Requires-Dist: attrs>=21.3.0
Provides-Extra: dev
Requires-Dist: furo; extra == "dev"
Requires-Dist: intersphinx-registry; extra == "dev"
Requires-Dist: packaging; extra == "dev"
Requires-Dist: pre-commit; extra == "dev"
Requires-Dist: pytest; extra == "dev"
Requires-Dist: pytest-cov; extra == "dev"
Requires-Dist: pytest-timeout; extra == "dev"
Requires-Dist: pytest-xdist; extra == "dev"
Requires-Dist: setuptools_scm; extra == "dev"
Requires-Dist: sphinx; extra == "dev"
Requires-Dist: sphinx_autodoc_typehints; extra == "dev"
Requires-Dist: sphinx-copybutton; extra == "dev"
Requires-Dist: sympy; extra == "dev"
Dynamic: license-file
